[{"word": "\u79bb\u5a5a", "pos": "v"}, {"word": "\u5973\u4eba", "pos": "n"}, {"word": "\u7684", "pos": "uj"}, {"word": "3", "pos": "m"}, {"word": "\u4e2a", "pos": "m"}, {"word": "\u597d\u5904", "pos": "d"}, {"word": "\u548c", "pos": "c"}, {"word": "3", "pos": "m"}, {"word": "\u4e2a", "pos": "m"}, {"word": "\u574f\u5904", "pos": "n"}, {"word": "\uff0c", "pos": "x"}, {"word": "\u660e\u767d", "pos": "nr"}, {"word": "\u4e86", "pos": "ul"}, {"word": "\u597d", "pos": "a"}, {"word": "\u4e0e", "pos": "p"}, {"word": "\u574f", "pos": "a"}, {"word": "\uff0c", "pos": "x"}, {"word": "\u518d\u5a36", "pos": "v"}, {"word": "\u4e5f", "pos": "d"}, {"word": "\u4e0d\u8fdf", "pos": "d"}, {"word": "\n", "pos": "x"}, {"word": "\n", "pos": "x"}, {"word": "\u6211", "pos": "r"}, {"word": "\u662f", "pos": "v"}, {"word": "\u5b66\u751f", "pos": "n"}]